mitnewsclassify/__init__.py
mitnewsclassify/distilbert.py
mitnewsclassify/doc2vec.py
mitnewsclassify/download.py
mitnewsclassify/ensemble.py
mitnewsclassify/gpt2.py
mitnewsclassify/gpt_model.py
mitnewsclassify/pentasemble.py
mitnewsclassify/quadsemble.py
mitnewsclassify/tfidf.py
mitnewsclassify/tfidf_bi.py
mitnewsclassify/trisemble.py
mitnewsclassify/utils.py
mit_news_classify-0.10.1.3.dist-info/LICENSE
mit_news_classify-0.10.1.3.dist-info/METADATA
mit_news_classify-0.10.1.3.dist-info/WHEEL
mit_news_classify-0.10.1.3.dist-info/top_level.txt
mit_news_classify-0.10.1.3.dist-info/RECORD
