Metadata-Version: 2.1
Name: mit-news-classify
Version: 0.10.1.3
Summary: A news classification tool developed for Improve the News, a project by Max Tegmark
Home-page: https://www.improvethenews.org/
Author: Arun Wongprommoon
Author-email: arunwpm@mit.edu
License: UNKNOWN
Platform: UNKNOWN
Classifier: Programming Language :: Python :: 3
Classifier: License :: OSI Approved :: MIT License
Classifier: Operating System :: OS Independent
Requires-Python: >=3.6
Requires-Dist: tensorflow (>=2.1)
Requires-Dist: sklearn
Requires-Dist: gensim (==3.8.3)
Requires-Dist: transformers
Requires-Dist: torch
Requires-Dist: numpy
Requires-Dist: tqdm
